{
  "response_code": 0,
  "results": [
    {
      "category": "Sports",
      "type": "multiple",
      "difficulty": "easy",
      "question": "Which of the following sports is not part of the triathlon?",
      "correct_answer": "Horse-Riding",
      "incorrect_answers": [
        "Cycling",
        "Swimming",
        "Running"
      ]
    },
    {
      "category": "Sports",
      "type": "multiple",
      "difficulty": "medium",
      "question": "At which bridge does the annual Oxford and Cambridge boat race start?",
      "correct_answer": "Putney",
      "incorrect_answers": [
        "Hammersmith",
        "Vauxhall ",
        "Battersea"
      ]
    },
    {
      "category": "Sports",
      "type": "multiple",
      "difficulty": "hard",
      "question": "How many times did Martina Navratilova win the Wimbledon Singles Championship?",
      "correct_answer": "Nine",
      "incorrect_answers": [
        "Ten",
        "Seven",
        "Eight"
      ]
    },
    {
      "category": "Sports",
      "type": "multiple",
      "difficulty": "medium",
      "question": "Which German sportswear company&#039;s logo is the &#039;Formstripe&#039;?",
      "correct_answer": "Puma",
      "incorrect_answers": [
        "Nike",
        "Adidas",
        "Reebok"
      ]
    },
    {
      "category": "Sports",
      "type": "multiple",
      "difficulty": "hard",
      "question": "What tool lends it&#039;s name to a last-stone advantage in an end in Curling?",
      "correct_answer": "Hammer",
      "incorrect_answers": [
        "Wrench",
        "Drill",
        "Screwdriver"
      ]
    },
    {
      "category": "Sports",
      "type": "multiple",
      "difficulty": "easy",
      "question": "In golf, what name is given to a hole score of two under par?",
      "correct_answer": "Eagle",
      "incorrect_answers": [
        "Birdie",
        "Bogey",
        "Albatross"
      ]
    },
    {
      "category": "Sports",
      "type": "multiple",
      "difficulty": "medium",
      "question": "What cricketing term denotes a batsman being dismissed with a score of zero?",
      "correct_answer": "Duck",
      "incorrect_answers": [
        "Bye",
        "Beamer",
        "Carry"
      ]
    },
    {
      "category": "Sports",
      "type": "multiple",
      "difficulty": "easy",
      "question": "Which English football club has the nickname &#039;The Foxes&#039;?",
      "correct_answer": "Leicester City",
      "incorrect_answers": [
        "Northampton Town",
        "Bradford City",
        "West Bromwich Albion"
      ]
    },
    {
      "category": "Sports",
      "type": "multiple",
      "difficulty": "easy",
      "question": "How many soccer players should be on the field at the same time?",
      "correct_answer": "22",
      "incorrect_answers": [
        "20",
        "24",
        "26"
      ]
    },
    {
      "category": "Sports",
      "type": "multiple",
      "difficulty": "easy",
      "question": "In what sport is a &quot;shuttlecock&quot; used?",
      "correct_answer": "Badminton",
      "incorrect_answers": [
        "Table Tennis",
        "Rugby",
        "Cricket"
      ]
    },
    {
      "category": "Sports",
      "type": "multiple",
      "difficulty": "medium",
      "question": "A stimpmeter measures the speed of a ball over what surface?",
      "correct_answer": "Golf Putting Green",
      "incorrect_answers": [
        " Football Pitch",
        "Cricket Outfield",
        "Pinball Table"
      ]
    },
    {
      "category": "Sports",
      "type": "multiple",
      "difficulty": "medium",
      "question": "In a game of snooker, what colour ball is worth 3 points?",
      "correct_answer": "Green",
      "incorrect_answers": [
        "Yellow",
        "Brown",
        "Blue"
      ]
    },
    {
      "category": "Sports",
      "type": "multiple",
      "difficulty": "hard",
      "question": "With which doubles partner did John McEnroe have most success?",
      "correct_answer": "Peter Fleming",
      "incorrect_answers": [
        "Mark Woodforde",
        "Michael Stich",
        "Mary Carillo"
      ]
    },
    {
      "category": "Sports",
      "type": "multiple",
      "difficulty": "easy",
      "question": "What was the final score of the Germany vs. Brazil 2014 FIFA World Cup match?",
      "correct_answer": "7 - 1",
      "incorrect_answers": [
        "0 - 1",
        "3 - 4",
        "16 - 0"
      ]
    },
    {
      "category": "Sports",
      "type": "multiple",
      "difficulty": "medium",
      "question": "Which team was the 2014-2015 NBA Champions?",
      "correct_answer": "Golden State Warriors",
      "incorrect_answers": [
        "Cleveland Cavaliers",
        "Houston Rockets",
        "Atlanta Hawks"
      ]
    },
    {
      "category": "Sports",
      "type": "multiple",
      "difficulty": "hard",
      "question": "Which female player won the gold medal of table tennis singles in 2016 Olympics Games?",
      "correct_answer": "DING Ning (China)",
      "incorrect_answers": [
        "LI Xiaoxia (China)",
        "Ai FUKUHARA (Japan)",
        "Song KIM (North Korea)"
      ]
    },
    {
      "category": "Sports",
      "type": "multiple",
      "difficulty": "medium",
      "question": "What national team won the 2016 edition of UEFA European Championship?",
      "correct_answer": "Portugal",
      "incorrect_answers": [
        "France",
        "Germany",
        "England"
      ]
    },
    {
      "category": "Sports",
      "type": "multiple",
      "difficulty": "medium",
      "question": "What is the oldest team in the NFL?",
      "correct_answer": "Arizona Cardinals",
      "incorrect_answers": [
        "Chicago Bears",
        "Green Bay Packers",
        "New York Giants"
      ]
    },
    {
      "category": "Sports",
      "type": "multiple",
      "difficulty": "easy",
      "question": "What year did the New Orleans Saints win the Super Bowl?",
      "correct_answer": "2010",
      "incorrect_answers": [
        "2008",
        "2009",
        "2011"
      ]
    },
    {
      "category": "Sports",
      "type": "multiple",
      "difficulty": "medium",
      "question": "What is the exact length of one non-curved part in Lane 1 of an Olympic Track?",
      "correct_answer": "84.39m",
      "incorrect_answers": [
        "100m",
        "100yd",
        "109.36yd"
      ]
    },
    {
      "category": "Sports",
      "type": "multiple",
      "difficulty": "easy",
      "question": "Which team has won the most Stanley Cups in the NHL?",
      "correct_answer": "Montreal Canadians",
      "incorrect_answers": [
        "Chicago Blackhawks",
        "Toronto Maple Leafs",
        "Detroit Red Wings"
      ]
    },
    {
      "category": "Sports",
      "type": "multiple",
      "difficulty": "medium",
      "question": "Who won the &quot;Champions League&quot; in 1999?",
      "correct_answer": "Manchester United",
      "incorrect_answers": [
        "Barcelona",
        "Bayern Munich",
        "Liverpool"
      ]
    },
    {
      "category": "Sports",
      "type": "multiple",
      "difficulty": "medium",
      "question": "Which of the following pitchers was named National League Rookie of the Year for the 2013 season?",
      "correct_answer": "Jose Fernandez",
      "incorrect_answers": [
        "Jacob deGrom",
        "Shelby Miller",
        "Matt Harvey"
      ]
    },
    {
      "category": "Sports",
      "type": "multiple",
      "difficulty": "medium",
      "question": "Why was The Green Monster at Fenway Park was originally built?",
      "correct_answer": "To prevent viewing games from outside the park.",
      "incorrect_answers": [
        "To make getting home runs harder.",
        "To display advertisements.",
        "To provide extra seating."
      ]
    },
    {
      "category": "Sports",
      "type": "multiple",
      "difficulty": "medium",
      "question": "Which NBA player won Most Valuable Player for the 1999-2000 season?",
      "correct_answer": "Shaquille O&#039;Neal",
      "incorrect_answers": [
        "Allen Iverson",
        "Kobe Bryant",
        "Paul Pierce"
      ]
    },
    {
      "category": "Sports",
      "type": "multiple",
      "difficulty": "medium",
      "question": "In what sport does Fanny Chmelar compete for Germany?",
      "correct_answer": "Skiing",
      "incorrect_answers": [
        "Swimming",
        "Showjumping",
        "Gymnastics"
      ]
    },
    {
      "category": "Sports",
      "type": "multiple",
      "difficulty": "easy",
      "question": "What is the most common type of pitch thrown by pitchers in baseball?",
      "correct_answer": "Fastball",
      "incorrect_answers": [
        "Slowball",
        "Screwball",
        "Palmball"
      ]
    },
    {
      "category": "Sports",
      "type": "multiple",
      "difficulty": "hard",
      "question": "What team did England beat in the semi-final stage to win in the 1966 World Cup final?",
      "correct_answer": "Portugal",
      "incorrect_answers": [
        "West Germany",
        "Soviet Union",
        "Brazil"
      ]
    },
    {
      "category": "Sports",
      "type": "multiple",
      "difficulty": "easy",
      "question": "In bowling, what is the term used for getting three consecutive strikes?",
      "correct_answer": "Turkey",
      "incorrect_answers": [
        "Flamingo",
        "Birdie",
        "Eagle"
      ]
    },
    {
      "category": "Sports",
      "type": "multiple",
      "difficulty": "easy",
      "question": "Who is often called &quot;the Maestro&quot; in the men&#039;s tennis circuit?",
      "correct_answer": "Roger Federer",
      "incorrect_answers": [
        "Bill Tilden",
        "Boris Becker",
        "Pete Sampras"
      ]
    },
    {
      "category": "Sports",
      "type": "multiple",
      "difficulty": "easy",
      "question": "Which African American is in part responsible for integrating  Major League baseball?",
      "correct_answer": "Jackie Robinson",
      "incorrect_answers": [
        "Curt Flood",
        "Roy Campanella",
        "Satchell Paige"
      ]
    },
    {
      "category": "Sports",
      "type": "multiple",
      "difficulty": "easy",
      "question": "Which player holds the NHL record of 2,857 points?",
      "correct_answer": "Wayne Gretzky",
      "incorrect_answers": [
        "Mario Lemieux ",
        "Sidney Crosby",
        "Gordie Howe"
      ]
    },
    {
      "category": "Sports",
      "type": "multiple",
      "difficulty": "hard",
      "question": "Which player &quot;kung-fu kicked&quot; a Crystal Palace fan in January 1995?",
      "correct_answer": "Eric Cantona",
      "incorrect_answers": [
        "David Seamen",
        "Ashley Cole",
        "Mark Hughes"
      ]
    },
    {
      "category": "Sports",
      "type": "multiple",
      "difficulty": "medium",
      "question": "Who is Manchester United&#039;s top premier league goal scorer?",
      "correct_answer": "Wayne Rooney",
      "incorrect_answers": [
        "Sir Bobby Charlton",
        "Ryan Giggs",
        "David Beckham"
      ]
    },
    {
      "category": "Sports",
      "type": "multiple",
      "difficulty": "easy",
      "question": "When was the FC Schalke 04 founded?",
      "correct_answer": "1904",
      "incorrect_answers": [
        "1909",
        "2008",
        "1999"
      ]
    },
    {
      "category": "Sports",
      "type": "multiple",
      "difficulty": "easy",
      "question": "The Los Angeles Dodgers were originally from what U.S. city?",
      "correct_answer": "Brooklyn",
      "incorrect_answers": [
        "Las Vegas",
        "Boston",
        "Seattle"
      ]
    },
    {
      "category": "Sports",
      "type": "multiple",
      "difficulty": "easy",
      "question": "Which country will host the 2022 FIFA World Cup?",
      "correct_answer": "Qatar",
      "incorrect_answers": [
        "USA",
        "Japan",
        "Switzerland"
      ]
    },
    {
      "category": "Sports",
      "type": "multiple",
      "difficulty": "medium",
      "question": "Which Formula 1 driver switched teams in the middle of the 2017 season?",
      "correct_answer": "Carlos Sainz Jr.",
      "incorrect_answers": [
        "Daniil Kvyat",
        "Jolyon Palmer",
        "Rio Haryanto"
      ]
    },
    {
      "category": "Sports",
      "type": "multiple",
      "difficulty": "medium",
      "question": "What is Tiger Woods&#039; all-time best career golf-score?",
      "correct_answer": "61",
      "incorrect_answers": [
        "65",
        "63",
        "67"
      ]
    },
    {
      "category": "Sports",
      "type": "multiple",
      "difficulty": "easy",
      "question": "Who won the UEFA Champions League in 2017?",
      "correct_answer": "Real Madrid C.F.",
      "incorrect_answers": [
        "Atletico Madrid",
        "AS Monaco FC",
        "Juventus F.C."
      ]
    },
    {
      "category": "Sports",
      "type": "multiple",
      "difficulty": "easy",
      "question": "In the 2014 FIFA World Cup, what was the final score in the match Brazil - Germany?",
      "correct_answer": "1-7",
      "incorrect_answers": [
        "1-5",
        "1-6",
        "2-6"
      ]
    },
    {
      "category": "Sports",
      "type": "multiple",
      "difficulty": "medium",
      "question": "Who won the 2011 Stanley Cup?",
      "correct_answer": "Boston Bruins",
      "incorrect_answers": [
        "Montreal Canadiens",
        "New York Rangers",
        "Toronto Maple Leafs"
      ]
    },
    {
      "category": "Sports",
      "type": "multiple",
      "difficulty": "medium",
      "question": "What is the name of the AHL affiliate of the Toronto Maple Leafs?",
      "correct_answer": "Toronto Marlies",
      "incorrect_answers": [
        "Toronto Rock",
        "Toronto Argonauts",
        "Toronto Wolfpack"
      ]
    },
    {
      "category": "Sports",
      "type": "multiple",
      "difficulty": "medium",
      "question": "What country hosted the 2014 Winter Olympics?",
      "correct_answer": "Russia",
      "incorrect_answers": [
        "Canada",
        "United States",
        "Germany"
      ]
    },
    {
      "category": "Sports",
      "type": "multiple",
      "difficulty": "medium",
      "question": "Which NBA player has the most games played over the course of their career?",
      "correct_answer": "Robert Parish",
      "incorrect_answers": [
        "Kareem Abdul-Jabbar",
        "Kevin Garnett",
        "Kobe Bryant"
      ]
    },
    {
      "category": "Sports",
      "type": "multiple",
      "difficulty": "medium",
      "question": "Which basketball team has attended the most NBA grand finals?",
      "correct_answer": "Los Angeles Lakers",
      "incorrect_answers": [
        "Boston Celtics",
        "Philadelphia 76ers",
        "Golden State Warriors"
      ]
    },
    {
      "category": "Sports",
      "type": "multiple",
      "difficulty": "medium",
      "question": "Which of these countries&#039; national teams qualified for the 2018 FIFA World Cup in Russia?",
      "correct_answer": "Tunisia",
      "incorrect_answers": [
        "United States of America",
        "Italy",
        "Netherlands"
      ]
    },
    {
      "category": "Sports",
      "type": "multiple",
      "difficulty": "hard",
      "question": "Which of these Russian cities did NOT contain a stadium that was used in the 2018 FIFA World Cup?",
      "correct_answer": "Vladivostok",
      "incorrect_answers": [
        "Rostov-on-Don",
        "Yekaterinburg",
        "Kaliningrad"
      ]
    },
    {
      "category": "Sports",
      "type": "multiple",
      "difficulty": "hard",
      "question": "In Canadian football, scoring a rouge is worth how many points?",
      "correct_answer": "1",
      "incorrect_answers": [
        "2",
        "3",
        "4"
      ]
    },
    {
      "category": "Sports",
      "type": "multiple",
      "difficulty": "hard",
      "question": "Which English football team is nicknamed &#039;The Tigers&#039;?",
      "correct_answer": "Hull City",
      "incorrect_answers": [
        "Cardiff City",
        "Bristol City",
        "Manchester City"
      ]
    },
    {
      "category": "Science: Computers",
      "type": "multiple",
      "difficulty": "easy",
      "question": "In any programming language, what is the most common way to iterate through an array?",
      "correct_answer": "&#039;For&#039; loops",
      "incorrect_answers": [
        "&#039;If&#039; Statements",
        "&#039;Do-while&#039; loops",
        "&#039;While&#039; loops"
      ]
    },
    {
      "category": "Science: Computers",
      "type": "multiple",
      "difficulty": "easy",
      "question": "What does CPU stand for?",
      "correct_answer": "Central Processing Unit",
      "incorrect_answers": [
        "Central Process Unit",
        "Computer Personal Unit",
        "Central Processor Unit"
      ]
    },
    {
      "category": "Science: Computers",
      "type": "multiple",
      "difficulty": "hard",
      "question": "What was the name of the security vulnerability found in Bash in 2014?",
      "correct_answer": "Shellshock",
      "incorrect_answers": [
        "Heartbleed",
        "Bashbug",
        "Stagefright"
      ]
    },
    {
      "category": "Science: Computers",
      "type": "multiple",
      "difficulty": "easy",
      "question": "When Gmail first launched, how much storage did it provide for your email?",
      "correct_answer": "1GB",
      "incorrect_answers": [
        "512MB",
        "5GB",
        "Unlimited"
      ]
    },
    {
      "category": "Science: Computers",
      "type": "multiple",
      "difficulty": "medium",
      "question": "Whistler was the codename of this Microsoft Operating System.",
      "correct_answer": "Windows XP",
      "incorrect_answers": [
        "Windows 2000",
        "Windows 7",
        "Windows 95"
      ]
    },
    {
      "category": "Science: Computers",
      "type": "multiple",
      "difficulty": "medium",
      "question": "Moore&#039;s law originally stated that the number of transistors on a microprocessor chip would double every...",
      "correct_answer": "Year",
      "incorrect_answers": [
        "Four Years",
        "Two Years",
        "Eight Years"
      ]
    },
    {
      "category": "Science: Computers",
      "type": "multiple",
      "difficulty": "easy",
      "question": "What does GHz stand for?",
      "correct_answer": "Gigahertz",
      "incorrect_answers": [
        "Gigahotz",
        "Gigahetz",
        "Gigahatz"
      ]
    },
    {
      "category": "Science: Computers",
      "type": "multiple",
      "difficulty": "medium",
      "question": "What does AD stand for in relation to Windows Operating Systems? ",
      "correct_answer": "Active Directory",
      "incorrect_answers": [
        "Alternative Drive",
        "Automated Database",
        "Active Department"
      ]
    },
    {
      "category": "Science: Computers",
      "type": "multiple",
      "difficulty": "medium",
      "question": "When was the programming language &quot;C#&quot; released?",
      "correct_answer": "2000",
      "incorrect_answers": [
        "1998",
        "1999",
        "2001"
      ]
    },
    {
      "category": "Science: Computers",
      "type": "multiple",
      "difficulty": "easy",
      "question": "What amount of bits commonly equals one byte?",
      "correct_answer": "8",
      "incorrect_answers": [
        "1",
        "2",
        "64"
      ]
    },
    {
      "category": "Science: Computers",
      "type": "multiple",
      "difficulty": "easy",
      "question": "In the programming language Java, which of these keywords would you put on a variable to make sure it doesn&#039;t get modified?",
      "correct_answer": "Final",
      "incorrect_answers": [
        "Static",
        "Private",
        "Public"
      ]
    },
    {
      "category": "Science: Computers",
      "type": "multiple",
      "difficulty": "easy",
      "question": "The series of the Intel HD graphics generation succeeding that of the 5000 and 6000 series (Broadwell) is called:",
      "correct_answer": "HD Graphics 500",
      "incorrect_answers": [
        "HD Graphics 700 ",
        "HD Graphics 600",
        "HD Graphics 7000"
      ]
    },
    {
      "category": "Science: Computers",
      "type": "multiple",
      "difficulty": "medium",
      "question": "Nvidia&#039;s headquarters are based in which Silicon Valley city?",
      "correct_answer": "Santa Clara",
      "incorrect_answers": [
        "Palo Alto",
        "Cupertino",
        "Mountain View"
      ]
    },
    {
      "category": "Science: Computers",
      "type": "multiple",
      "difficulty": "medium",
      "question": "What was the name given to Android 4.3?",
      "correct_answer": "Jelly Bean",
      "incorrect_answers": [
        "Lollipop",
        "Nutella",
        "Froyo"
      ]
    },
    {
      "category": "Science: Computers",
      "type": "multiple",
      "difficulty": "easy",
      "question": "What is the domain name for the country Tuvalu?",
      "correct_answer": ".tv",
      "incorrect_answers": [
        ".tu",
        ".tt",
        ".tl"
      ]
    },
    {
      "category": "Science: Computers",
      "type": "multiple",
      "difficulty": "hard",
      "question": "The internet domain .fm is the country-code top-level domain for which Pacific Ocean island nation?",
      "correct_answer": "Micronesia",
      "incorrect_answers": [
        "Fiji",
        "Tuvalu",
        "Marshall Islands"
      ]
    },
    {
      "category": "Science: Computers",
      "type": "multiple",
      "difficulty": "easy",
      "question": "How many kilobytes in one gigabyte (in decimal)?",
      "correct_answer": "1000000",
      "incorrect_answers": [
        "1024",
        "1000",
        "1048576"
      ]
    },
    {
      "category": "Science: Computers",
      "type": "multiple",
      "difficulty": "medium",
      "question": "Which one of these is not an official development name for a Ubuntu release?",
      "correct_answer": "Mystic Mansion",
      "incorrect_answers": [
        "Trusty Tahr",
        "Utopic Unicorn",
        "Wily Werewolf"
      ]
    },
    {
      "category": "Science: Computers",
      "type": "multiple",
      "difficulty": "medium",
      "question": "What is the name of the default theme that is installed with Windows XP?",
      "correct_answer": "Luna",
      "incorrect_answers": [
        "Neptune",
        "Whistler",
        "Bliss"
      ]
    },
    {
      "category": "Science: Computers",
      "type": "multiple",
      "difficulty": "medium",
      "question": "In the programming language &quot;Python&quot;, which of these statements would display the string &quot;Hello World&quot; correctly?",
      "correct_answer": "print(&quot;Hello World&quot;)",
      "incorrect_answers": [
        "console.log(&quot;Hello World&quot;)",
        "echo &quot;Hello World&quot;",
        "printf(&quot;Hello World&quot;)"
      ]
    },
    {
      "category": "Science: Computers",
      "type": "multiple",
      "difficulty": "medium",
      "question": "In HTML, which non-standard tag used to be be used to make elements scroll across the viewport?",
      "correct_answer": "&lt;marquee&gt;&lt;/marquee&gt;",
      "incorrect_answers": [
        "&lt;scroll&gt;&lt;/scroll&gt;",
        "&lt;move&gt;&lt;/move&gt;",
        "&lt;slide&gt;&lt;/slide&gt;"
      ]
    },
    {
      "category": "Science: Computers",
      "type": "multiple",
      "difficulty": "easy",
      "question": "Which computer language would you associate Django framework with?",
      "correct_answer": "Python",
      "incorrect_answers": [
        "C#",
        "C++",
        "Java"
      ]
    },
    {
      "category": "Science: Computers",
      "type": "multiple",
      "difficulty": "medium",
      "question": "Which of these programming languages is a low-level language?",
      "correct_answer": "Assembly",
      "incorrect_answers": [
        "Python",
        "C#",
        "Pascal"
      ]
    },
    {
      "category": "Science: Computers",
      "type": "multiple",
      "difficulty": "medium",
      "question": "In computing terms, typically what does CLI stand for?",
      "correct_answer": "Command Line Interface",
      "incorrect_answers": [
        "Common Language Input",
        "Control Line Interface",
        "Common Language Interface"
      ]
    },
    {
      "category": "Science: Computers",
      "type": "multiple",
      "difficulty": "medium",
      "question": "How fast is USB 3.1 Gen 2 theoretically?",
      "correct_answer": "10 Gb/s",
      "incorrect_answers": [
        "5 Gb/s",
        "8 Gb/s",
        "1 Gb/s"
      ]
    },
    {
      "category": "Science: Computers",
      "type": "multiple",
      "difficulty": "medium",
      "question": "What does &quot;LCD&quot; stand for?",
      "correct_answer": "Liquid Crystal Display",
      "incorrect_answers": [
        "Language Control Design",
        "Last Common Difference",
        "Long Continuous Design"
      ]
    },
    {
      "category": "Science: Computers",
      "type": "multiple",
      "difficulty": "hard",
      "question": "Who is the original author of the realtime physics engine called PhysX?",
      "correct_answer": "NovodeX",
      "incorrect_answers": [
        "Ageia",
        "Nvidia",
        "AMD"
      ]
    },
    {
      "category": "Science: Computers",
      "type": "multiple",
      "difficulty": "medium",
      "question": ".rs is the top-level domain for what country?",
      "correct_answer": "Serbia",
      "incorrect_answers": [
        "Romania",
        "Russia",
        "Rwanda"
      ]
    },
    {
      "category": "Science: Computers",
      "type": "multiple",
      "difficulty": "easy",
      "question": "The numbering system with a radix of 16 is more commonly referred to as ",
      "correct_answer": "Hexidecimal",
      "incorrect_answers": [
        "Binary",
        "Duodecimal",
        "Octal"
      ]
    },
    {
      "category": "Science: Computers",
      "type": "multiple",
      "difficulty": "hard",
      "question": "Which of the following is the oldest of these computers by release date?",
      "correct_answer": "TRS-80",
      "incorrect_answers": [
        "Commodore 64",
        "ZX Spectrum",
        "Apple 3"
      ]
    },
    {
      "category": "Science: Computers",
      "type": "multiple",
      "difficulty": "hard",
      "question": "What is the name of the process that sends one qubit of information using two bits of classical information?",
      "correct_answer": "Quantum Teleportation",
      "incorrect_answers": [
        "Super Dense Coding",
        "Quantum Entanglement",
        "Quantum Programming"
      ]
    },
    {
      "category": "Science: Computers",
      "type": "multiple",
      "difficulty": "hard",
      "question": "America Online (AOL) started out as which of these online service providers?",
      "correct_answer": "Quantum Link",
      "incorrect_answers": [
        "CompuServe",
        "Prodigy",
        "GEnie"
      ]
    },
    {
      "category": "Science: Computers",
      "type": "multiple",
      "difficulty": "hard",
      "question": "What internet protocol was documented in RFC 1459?",
      "correct_answer": "IRC",
      "incorrect_answers": [
        "HTTP",
        "HTTPS",
        "FTP"
      ]
    },
    {
      "category": "Science: Computers",
      "type": "multiple",
      "difficulty": "medium",
      "question": "What is the main CPU is the Sega Mega Drive / Sega Genesis?",
      "correct_answer": "Motorola 68000",
      "incorrect_answers": [
        "Zilog Z80",
        "Yamaha YM2612",
        "Intel 8088"
      ]
    },
    {
      "category": "Science: Computers",
      "type": "multiple",
      "difficulty": "medium",
      "question": "Laserjet and inkjet printers are both examples of what type of printer?",
      "correct_answer": "Non-impact printer",
      "incorrect_answers": [
        "Impact printer",
        "Daisywheel printer",
        "Dot matrix printer"
      ]
    },
    {
      "category": "Science: Computers",
      "type": "multiple",
      "difficulty": "hard",
      "question": "Dutch computer scientist Mark Overmars is known for creating which game development engine?",
      "correct_answer": "Game Maker",
      "incorrect_answers": [
        "Stencyl",
        "Construct",
        "Torque 2D"
      ]
    },
    {
      "category": "Science: Computers",
      "type": "multiple",
      "difficulty": "medium",
      "question": "Which programming language was developed by Sun Microsystems in 1995?",
      "correct_answer": "Java",
      "incorrect_answers": [
        "Python",
        "Solaris OS",
        "C++"
      ]
    },
    {
      "category": "Science: Computers",
      "type": "multiple",
      "difficulty": "hard",
      "question": "What is the name given to layer 4 of the Open Systems Interconnection (ISO) model?",
      "correct_answer": "Transport",
      "incorrect_answers": [
        "Session",
        "Data link",
        "Network"
      ]
    },
    {
      "category": "Science: Computers",
      "type": "multiple",
      "difficulty": "hard",
      "question": "Who invented the &quot;Spanning Tree Protocol&quot;?",
      "correct_answer": "Radia Perlman",
      "incorrect_answers": [
        "Paul Vixie",
        "Vint Cerf",
        "Michael Roberts"
      ]
    },
    {
      "category": "Science: Computers",
      "type": "multiple",
      "difficulty": "medium",
      "question": "Approximately how many Apple I personal computers were created?",
      "correct_answer": "200",
      "incorrect_answers": [
        "100",
        "500",
        "1000"
      ]
    },
    {
      "category": "Science: Computers",
      "type": "multiple",
      "difficulty": "easy",
      "question": "Which programming language shares its name with an island in Indonesia?",
      "correct_answer": "Java",
      "incorrect_answers": [
        "Python",
        "C",
        "Jakarta"
      ]
    },
    {
      "category": "Science: Computers",
      "type": "multiple",
      "difficulty": "easy",
      "question": "In computing, what does MIDI stand for?",
      "correct_answer": "Musical Instrument Digital Interface",
      "incorrect_answers": [
        "Musical Interface of Digital Instruments",
        "Modular Interface of Digital Instruments",
        "Musical Instrument Data Interface"
      ]
    },
    {
      "category": "Science: Computers",
      "type": "multiple",
      "difficulty": "hard",
      "question": "The acronym &quot;RIP&quot; stands for which of these?",
      "correct_answer": "Routing Information Protocol",
      "incorrect_answers": [
        "Runtime Instance Processes",
        "Regular Interval Processes",
        "Routine Inspection Protocol"
      ]
    },
    {
      "category": "Science: Computers",
      "type": "multiple",
      "difficulty": "hard",
      "question": "Which of these is not a layer in the OSI model for data communications?",
      "correct_answer": "Connection Layer",
      "incorrect_answers": [
        "Application Layer",
        "Transport Layer",
        "Physical Layer"
      ]
    },
    {
      "category": "Science: Computers",
      "type": "multiple",
      "difficulty": "hard",
      "question": "What was the name of the first Bulgarian personal computer?",
      "correct_answer": "IMKO-1",
      "incorrect_answers": [
        "Pravetz 82",
        "Pravetz 8D",
        "IZOT 1030"
      ]
    },
    {
      "category": "Science: Computers",
      "type": "multiple",
      "difficulty": "medium",
      "question": "How many bits make up the significand portion of a single precision floating point number?",
      "correct_answer": "23",
      "incorrect_answers": [
        "8",
        "53",
        "15"
      ]
    },
    {
      "category": "Science: Computers",
      "type": "multiple",
      "difficulty": "medium",
      "question": "What does the &#039;S&#039; in the RSA encryption algorithm stand for?",
      "correct_answer": "Shamir",
      "incorrect_answers": [
        "Secure",
        "Schottky",
        "Stable"
      ]
    },
    {
      "category": "Science: Computers",
      "type": "multiple",
      "difficulty": "easy",
      "question": "What language does Node.js use?",
      "correct_answer": "JavaScript",
      "incorrect_answers": [
        "Java",
        "Java Source",
        "Joomla Source Code"
      ]
    },
    {
      "category": "Science: Computers",
      "type": "multiple",
      "difficulty": "hard",
      "question": "Lenovo acquired IBM&#039;s personal computer division, including the ThinkPad line of laptops and tablets, in what year?",
      "correct_answer": "2005",
      "incorrect_answers": [
        "1999",
        "2002",
        "2008"
      ]
    },
    {
      "category": "Science: Computers",
      "type": "multiple",
      "difficulty": "easy",
      "question": "What does the computer software acronym JVM stand for?",
      "correct_answer": "Java Virtual Machine",
      "incorrect_answers": [
        "Java Vendor Machine",
        "Java Visual Machine",
        "Just Virtual Machine"
      ]
    },
    {
      "category": "Mythology",
      "type": "multiple",
      "difficulty": "hard",
      "question": "What was the punishment for Sysiphus&#039;s craftiness?",
      "correct_answer": "Cursed to roll a boulder up a hill for eternity.",
      "incorrect_answers": [
        "Tied to a boulder for eternity, being pecked by birds.",
        "Standing in a lake filled with water he could not drink.",
        "To fell a tree that regenerated after every axe swing."
      ]
    },
    {
      "category": "Mythology",
      "type": "multiple",
      "difficulty": "hard",
      "question": "According to Algonquian folklore, how does one transform into a Wendigo?",
      "correct_answer": "Participating in cannibalism.",
      "incorrect_answers": [
        "Excessive mutilation of animal corpses.",
        "Performing a ritual involving murder.",
        "Drinking the blood of many slain animals."
      ]
    },
    {
      "category": "Mythology",
      "type": "multiple",
      "difficulty": "easy",
      "question": "Who was the only god from Greece who did not get a name change in Rome?",
      "correct_answer": "Apollo",
      "incorrect_answers": [
        "Demeter",
        "Zeus",
        "Athena"
      ]
    },
    {
      "category": "Mythology",
      "type": "multiple",
      "difficulty": "easy",
      "question": "The ancient Roman god of war was commonly known as which of the following?",
      "correct_answer": "Mars",
      "incorrect_answers": [
        "Jupiter",
        "Juno",
        "Ares"
      ]
    },
    {
      "category": "Mythology",
      "type": "multiple",
      "difficulty": "medium",
      "question": "This Greek mythological figure is the god/goddess of battle strategy (among other things).",
      "correct_answer": "Athena",
      "incorrect_answers": [
        "Ares",
        "Artemis",
        "Apollo"
      ]
    },
    {
      "category": "Mythology",
      "type": "boolean",
      "difficulty": "easy",
      "question": "In Norse mythology, Thor once dressed as a woman.",
      "correct_answer": "True",
      "incorrect_answers": [
        "False"
      ]
    },
    {
      "category": "Mythology",
      "type": "multiple",
      "difficulty": "medium",
      "question": "The Hippogriff, not to be confused with the Griffon, is a magical creature with the front half of an eagle, and the back half of what?",
      "correct_answer": "A Horse",
      "incorrect_answers": [
        "A Dragon",
        "A Tiger",
        "A Lion"
      ]
    },
    {
      "category": "Mythology",
      "type": "multiple",
      "difficulty": "medium",
      "question": "Who was the Roman god of fire?",
      "correct_answer": "Vulcan",
      "incorrect_answers": [
        "Apollo",
        "Jupiter",
        "Mercury"
      ]
    },
    {
      "category": "Mythology",
      "type": "multiple",
      "difficulty": "medium",
      "question": "Hera is god of...",
      "correct_answer": "Marriage",
      "incorrect_answers": [
        "Agriculture",
        "Sea",
        "War"
      ]
    },
    {
      "category": "Mythology",
      "type": "multiple",
      "difficulty": "medium",
      "question": "Which of the following Mesopotamian mythological figures was NOT a deity?",
      "correct_answer": "Enkidu",
      "incorrect_answers": [
        "Enki",
        "Enlil",
        "Enkimdu"
      ]
    },
    {
      "category": "Mythology",
      "type": "multiple",
      "difficulty": "easy",
      "question": "This Greek goddess&#039;s name was chosen for the dwarf planet responsible for discord on Pluto&#039;s classification amongst astronomers.",
      "correct_answer": "Eris",
      "incorrect_answers": [
        "Charon",
        "Ceres",
        "Dysnomia"
      ]
    },
    {
      "category": "Mythology",
      "type": "multiple",
      "difficulty": "hard",
      "question": "In Greek Mythology, who was the daughter of King Minos?",
      "correct_answer": "Ariadne",
      "incorrect_answers": [
        "Athena",
        "Ariel",
        "Alana"
      ]
    },
    {
      "category": "Mythology",
      "type": "boolean",
      "difficulty": "easy",
      "question": "According to Greek Mythology, Zeus can control lightning.",
      "correct_answer": "True",
      "incorrect_answers": [
        "False"
      ]
    },
    {
      "category": "Mythology",
      "type": "boolean",
      "difficulty": "medium",
      "question": "According to Norse mythology, Loki is a mother.",
      "correct_answer": "True",
      "incorrect_answers": [
        "False"
      ]
    },
    {
      "category": "Mythology",
      "type": "boolean",
      "difficulty": "medium",
      "question": "The Japanese god Izanagi successfully returned his wife Izanami from the Underworld.",
      "correct_answer": "False",
      "incorrect_answers": [
        "True"
      ]
    },
    {
      "category": "Mythology",
      "type": "multiple",
      "difficulty": "hard",
      "question": "In Norse mythology, what is the name of the serpent which eats the roots of the ash tree Yggdrasil?",
      "correct_answer": "Nidhogg",
      "incorrect_answers": [
        "Bragi",
        "Odin",
        "Ymir"
      ]
    },
    {
      "category": "Mythology",
      "type": "multiple",
      "difficulty": "medium",
      "question": "Which of these Roman gods doesn&#039;t have a counterpart in Greek mythology?",
      "correct_answer": "Janus",
      "incorrect_answers": [
        "Vulcan",
        "Juno",
        "Mars"
      ]
    },
    {
      "category": "Mythology",
      "type": "multiple",
      "difficulty": "easy",
      "question": "Which Greek &amp; Roman god was known as the god of music, truth and prophecy, healing, the sun and light, plague, poetry, and more?",
      "correct_answer": "Apollo",
      "incorrect_answers": [
        "Aphrodite",
        "Artemis",
        "Athena"
      ]
    },
    {
      "category": "Mythology",
      "type": "boolean",
      "difficulty": "hard",
      "question": "Rannamaari was a sea demon that haunted the people of the Maldives and had to be appeased monthly with the sacrifice of a virgin girl.",
      "correct_answer": "True",
      "incorrect_answers": [
        "False"
      ]
    },
    {
      "category": "Mythology",
      "type": "multiple",
      "difficulty": "medium",
      "question": "In Greek Mythology, who killed Achilles?",
      "correct_answer": "Paris",
      "incorrect_answers": [
        "Hector",
        "Helen",
        "Pericles"
      ]
    },
    {
      "category": "Mythology",
      "type": "multiple",
      "difficulty": "easy",
      "question": "Which figure from Greek mythology traveled to the underworld to return his wife Eurydice to the land of the living?",
      "correct_answer": "Orpheus",
      "incorrect_answers": [
        "Hercules",
        "Perseus",
        "Daedalus"
      ]
    },
    {
      "category": "Mythology",
      "type": "multiple",
      "difficulty": "hard",
      "question": "Which of the following is NOT a god in Norse Mythology.",
      "correct_answer": "Jens",
      "incorrect_answers": [
        "Loki",
        "Tyr",
        "Snotra"
      ]
    },
    {
      "category": "Mythology",
      "type": "multiple",
      "difficulty": "hard",
      "question": "Nidhogg is a mythical creature from what mythology?",
      "correct_answer": "Norse",
      "incorrect_answers": [
        "Egyptian",
        "Greek",
        "Hindu"
      ]
    },
    {
      "category": "Mythology",
      "type": "boolean",
      "difficulty": "medium",
      "question": "In Greek mythology, Hera is the goddess of harvest.",
      "correct_answer": "False",
      "incorrect_answers": [
        "True"
      ]
    },
    {
      "category": "Mythology",
      "type": "multiple",
      "difficulty": "easy",
      "question": "In Greek mythology, who is the god of wine?",
      "correct_answer": "Dionysus",
      "incorrect_answers": [
        "Hephaestus",
        "Demeter",
        "Apollo"
      ]
    },
    {
      "category": "Mythology",
      "type": "multiple",
      "difficulty": "hard",
      "question": "Who is the Egyptian god of reproduction and lettuce?",
      "correct_answer": "Min",
      "incorrect_answers": [
        "Menu",
        "Mut",
        "Meret"
      ]
    },
    {
      "category": "Mythology",
      "type": "multiple",
      "difficulty": "medium",
      "question": "A minotaur is half human half what?",
      "correct_answer": "Bull",
      "incorrect_answers": [
        "Cow",
        "Horse",
        "Eagle"
      ]
    },
    {
      "category": "Mythology",
      "type": "boolean",
      "difficulty": "easy",
      "question": "According to Greek Mythology, Atlas was an Olympian God.",
      "correct_answer": "False",
      "incorrect_answers": [
        "True"
      ]
    },
    {
      "category": "Mythology",
      "type": "multiple",
      "difficulty": "medium",
      "question": "What is the name of the Greek god of blacksmiths?",
      "correct_answer": "Hephaestus",
      "incorrect_answers": [
        "Dyntos",
        "Vulcan",
        "Artagatus"
      ]
    },
    {
      "category": "Mythology",
      "type": "multiple",
      "difficulty": "medium",
      "question": "According to the Egyptian Myth of Osiris, who murdered Osiris?",
      "correct_answer": "Set",
      "incorrect_answers": [
        "Horus",
        "Ra",
        "Anhur"
      ]
    },
    {
      "category": "Mythology",
      "type": "boolean",
      "difficulty": "medium",
      "question": "The Roman god &quot;Jupiter&quot; was first known as &quot;Zeus&quot; to the Greeks.",
      "correct_answer": "True",
      "incorrect_answers": [
        "False"
      ]
    },
    {
      "category": "Mythology",
      "type": "multiple",
      "difficulty": "easy",
      "question": "Which of these mythological creatures is said to be half-man and half-horse?",
      "correct_answer": "Centaur",
      "incorrect_answers": [
        "Minotaur",
        "Pegasus",
        "Gorgon"
      ]
    },
    {
      "category": "Mythology",
      "type": "multiple",
      "difficulty": "medium",
      "question": "Which of the following is not one of the Greek Fates?",
      "correct_answer": "Narcissus",
      "incorrect_answers": [
        "Clotho",
        "Atropos",
        "Lachesis"
      ]
    },
    {
      "category": "Mythology",
      "type": "multiple",
      "difficulty": "easy",
      "question": "What mythology did the god &quot;Apollo&quot; come from?",
      "correct_answer": "Greek and Roman",
      "incorrect_answers": [
        "Roman and Spanish",
        "Greek and Chinese",
        "Greek, Roman and Norse"
      ]
    },
    {
      "category": "Mythology",
      "type": "multiple",
      "difficulty": "medium",
      "question": "In African mythology, Anansi is a trickster and storyteller who takes the shape of which animal?",
      "correct_answer": "Spider",
      "incorrect_answers": [
        "Wild dog",
        "Monkey",
        "Crocodile"
      ]
    },
    {
      "category": "Mythology",
      "type": "multiple",
      "difficulty": "medium",
      "question": "The Maori hold that which island nation was founded by Kupe, who discovered it under a long white cloud?",
      "correct_answer": "New Zealand",
      "incorrect_answers": [
        "Vanuatu",
        "Fiji",
        "Hawaii"
      ]
    },
    {
      "category": "Mythology",
      "type": "boolean",
      "difficulty": "easy",
      "question": "A wyvern is the same as a dragon.",
      "correct_answer": "False",
      "incorrect_answers": [
        "True"
      ]
    },
    {
      "category": "Mythology",
      "type": "multiple",
      "difficulty": "easy",
      "question": "What mytological creatures have women&#039;s faces and vultures&#039; bodies?",
      "correct_answer": "Harpies",
      "incorrect_answers": [
        "Mermaids",
        "Nymph",
        "Lilith"
      ]
    },
    {
      "category": "Mythology",
      "type": "boolean",
      "difficulty": "hard",
      "question": "Janus was the Roman god of doorways and passageways.",
      "correct_answer": "True",
      "incorrect_answers": [
        "False"
      ]
    },
    {
      "category": "Mythology",
      "type": "multiple",
      "difficulty": "medium",
      "question": "Who is the god of war in Polynesian mythology?",
      "correct_answer": "&#039;Oro",
      "incorrect_answers": [
        "Hina",
        "Kohara",
        "Māui"
      ]
    },
    {
      "category": "Mythology",
      "type": "multiple",
      "difficulty": "hard",
      "question": "What immense structure is referred to in Norse Mythology as the Yggdrasil.",
      "correct_answer": "Tree",
      "incorrect_answers": [
        "Mountain",
        "Temple",
        "Castle"
      ]
    },
    {
      "category": "Mythology",
      "type": "multiple",
      "difficulty": "easy",
      "question": "The Nike apparel and footwear brand takes it&#039;s name from the Greek goddess of what?",
      "correct_answer": "Victory",
      "incorrect_answers": [
        "Courage",
        "Strength",
        "Honor"
      ]
    },
    {
      "category": "Mythology",
      "type": "multiple",
      "difficulty": "medium",
      "question": "According to Japanese folklore, what is the favorite food of the Kappa.",
      "correct_answer": "Cucumbers",
      "incorrect_answers": [
        "Kabocha",
        "Nasu",
        "Soba"
      ]
    },
    {
      "category": "Mythology",
      "type": "multiple",
      "difficulty": "hard",
      "question": "Which Norse God has a horse named Sleipnir?",
      "correct_answer": "Odin",
      "incorrect_answers": [
        "Thor",
        "Frigg",
        "Balder"
      ]
    },
    {
      "category": "Mythology",
      "type": "multiple",
      "difficulty": "medium",
      "question": "The Norse god Odin has two pet crows named &quot;Huginn&quot; and &quot;Muninn&quot;.  What do their names mean?",
      "correct_answer": "Thought &amp; Memory",
      "incorrect_answers": [
        "Power &amp; Peace",
        "War &amp; Learning",
        "Sleeping &amp; Waking"
      ]
    },
    {
      "category": "Mythology",
      "type": "multiple",
      "difficulty": "medium",
      "question": "What is the name of the first human being in Norse mythology?",
      "correct_answer": "Ask",
      "incorrect_answers": [
        "Asmund",
        "Ake",
        "Asger"
      ]
    },
    {
      "category": "Mythology",
      "type": "multiple",
      "difficulty": "medium",
      "question": "Which greek god/goddess tossed a golden apple with the words &quot;for the fairest&quot; into the middle of the feast of the gods?",
      "correct_answer": "Eris",
      "incorrect_answers": [
        "Hades",
        "Ares",
        "Artemis"
      ]
    },
    {
      "category": "Mythology",
      "type": "multiple",
      "difficulty": "medium",
      "question": "What is the name of the Greek god of peaceful deaths?",
      "correct_answer": "Thanatos",
      "incorrect_answers": [
        "Tartarus",
        "Hades",
        "Moros"
      ]
    },
    {
      "category": "Mythology",
      "type": "multiple",
      "difficulty": "medium",
      "question": "What animal did Queen Pasipahe sleep with before she gave birth to the Minotaur in Greek Mythology?",
      "correct_answer": "Bull",
      "incorrect_answers": [
        "Pig",
        "Ox",
        "Horse"
      ]
    },
    {
      "category": "Mythology",
      "type": "multiple",
      "difficulty": "hard",
      "question": "Who is a minor god that is protector and creator of various arts, such as cheese making and bee keeping.",
      "correct_answer": "Aristaeus",
      "incorrect_answers": [
        "Autonoe",
        "Carme",
        "Cephisso"
      ]
    },
    {
      "category": "History",
      "type": "multiple",
      "difficulty": "easy",
      "question": "King Henry VIII was the second monarch of which European royal house?",
      "correct_answer": "Tudor",
      "incorrect_answers": [
        "York",
        "Stuart",
        "Lancaster"
      ]
    },
    {
      "category": "History",
      "type": "multiple",
      "difficulty": "hard",
      "question": "Pianist Fr&eacute;d&eacute;ric Chopin was a composer of which musical era?",
      "correct_answer": "Romantic",
      "incorrect_answers": [
        "Classic",
        "Baroque",
        "Renaissance"
      ]
    },
    {
      "category": "History",
      "type": "multiple",
      "difficulty": "hard",
      "question": "In the year 1900, what were the most popular first names given to boy and girl babies born in the United States?",
      "correct_answer": "John and Mary",
      "incorrect_answers": [
        "Joseph and Catherine",
        "William and Elizabeth",
        "George and Anne"
      ]
    },
    {
      "category": "History",
      "type": "multiple",
      "difficulty": "easy",
      "question": "Who discovered Penicillin?",
      "correct_answer": "Alexander Flemming",
      "incorrect_answers": [
        "Marie Curie",
        "Alfred Nobel",
        "Louis Pasteur"
      ]
    },
    {
      "category": "History",
      "type": "multiple",
      "difficulty": "easy",
      "question": "How many manned moon landings have there been?",
      "correct_answer": "6",
      "incorrect_answers": [
        "1",
        "3",
        "7"
      ]
    },
    {
      "category": "History",
      "type": "multiple",
      "difficulty": "medium",
      "question": "America&#039;s Strategic Defense System during the Cold War was nicknamed after this famous movie.",
      "correct_answer": "Star Wars",
      "incorrect_answers": [
        "Jaws",
        "Blade Runner",
        "Alien"
      ]
    },
    {
      "category": "History",
      "type": "multiple",
      "difficulty": "medium",
      "question": "The Tsar Bomba, the most powerful nuclear bomb ever tested, had a yield of 50 megatons but theoretically had a maximum yield of how much?",
      "correct_answer": "100 Megatons",
      "incorrect_answers": [
        "200 Megatons",
        "75 Megatons",
        "150 Megatons"
      ]
    },
    {
      "category": "History",
      "type": "multiple",
      "difficulty": "easy",
      "question": "In what year did the Wall Street Crash take place?",
      "correct_answer": "1929",
      "incorrect_answers": [
        "1932",
        "1930",
        "1925"
      ]
    },
    {
      "category": "History",
      "type": "multiple",
      "difficulty": "medium",
      "question": "In what year was the famous 45 foot tall Hollywood sign first erected?",
      "correct_answer": "1923",
      "incorrect_answers": [
        "1903",
        "1913",
        "1933"
      ]
    },
    {
      "category": "History",
      "type": "multiple",
      "difficulty": "medium",
      "question": "The crown of the Empire State Building was originally built for what purpose?",
      "correct_answer": "Airship Dock",
      "incorrect_answers": [
        "Lightning Rod",
        "Antennae",
        "Flag Pole"
      ]
    },
    {
      "category": "History",
      "type": "multiple",
      "difficulty": "hard",
      "question": "When did Spanish Peninsular War start?",
      "correct_answer": "1808",
      "incorrect_answers": [
        "1806",
        "1810",
        "1809"
      ]
    },
    {
      "category": "History",
      "type": "multiple",
      "difficulty": "medium",
      "question": "The Battle of the Somme in World War I took place in which country?",
      "correct_answer": "France",
      "incorrect_answers": [
        "Germany",
        "Italy",
        "Austria"
      ]
    },
    {
      "category": "History",
      "type": "multiple",
      "difficulty": "medium",
      "question": "The Herero genocide was perpetrated in Africa by which of the following colonial nations?",
      "correct_answer": "Germany",
      "incorrect_answers": [
        "Britain",
        "Belgium",
        "France"
      ]
    },
    {
      "category": "History",
      "type": "multiple",
      "difficulty": "easy",
      "question": "What was Manfred von Richthofen&#039;s nickname?",
      "correct_answer": "The Red Baron",
      "incorrect_answers": [
        "The High Flying Ace",
        "The Blue Serpent ",
        "The Germany Gunner"
      ]
    },
    {
      "category": "History",
      "type": "multiple",
      "difficulty": "medium",
      "question": "When was &quot;The Gadget&quot;, the first nuclear device to be detonated, tested?",
      "correct_answer": "July 16, 1945",
      "incorrect_answers": [
        "June 22, 1945",
        "August 6, 1945",
        "April 5, 1945"
      ]
    },
    {
      "category": "History",
      "type": "multiple",
      "difficulty": "medium",
      "question": "On which day did the attempted coup d&#039;etat of 1991 in the Soviet Union begin?",
      "correct_answer": "August 19",
      "incorrect_answers": [
        "August 21",
        "December 26",
        "December 24"
      ]
    },
    {
      "category": "History",
      "type": "multiple",
      "difficulty": "easy",
      "question": "In which year did the Invasion of Kuwait by Iraq occur?",
      "correct_answer": "1990",
      "incorrect_answers": [
        "1992",
        "1988",
        "1986"
      ]
    },
    {
      "category": "History",
      "type": "multiple",
      "difficulty": "easy",
      "question": "When did the Battle of the Somme begin?",
      "correct_answer": "July 1st, 1916",
      "incorrect_answers": [
        "August 1st, 1916",
        "July 2nd, 1916",
        "June 30th, 1916"
      ]
    },
    {
      "category": "History",
      "type": "multiple",
      "difficulty": "medium",
      "question": "What year were the Marian Reforms instituted in the Roman Republic?",
      "correct_answer": "107 BCE",
      "incorrect_answers": [
        "42 BCE",
        "264 BCE",
        "102 CE"
      ]
    },
    {
      "category": "History",
      "type": "multiple",
      "difficulty": "hard",
      "question": "What was the real name of the Albanian national leader Skanderbeg?",
      "correct_answer": "Gjergj Kastrioti",
      "incorrect_answers": [
        "Diturak Zhulati",
        "Iskander Bejko",
        "Mirash Krasniki"
      ]
    },
    {
      "category": "History",
      "type": "multiple",
      "difficulty": "medium",
      "question": "What is the oldest US state?",
      "correct_answer": "Delaware",
      "incorrect_answers": [
        "Rhode Island",
        "Maine",
        "Virginia"
      ]
    },
    {
      "category": "History",
      "type": "multiple",
      "difficulty": "hard",
      "question": "When did Lithuania declare independence from the Soviet Union?",
      "correct_answer": "March 11th, 1990",
      "incorrect_answers": [
        "December 25th, 1991",
        "December 5th, 1991",
        "April 20th, 1989"
      ]
    },
    {
      "category": "History",
      "type": "multiple",
      "difficulty": "medium",
      "question": "What was the transfer of disease, crops, and people across the Atlantic shortly after the discovery of the Americas called?",
      "correct_answer": "The Columbian Exchange",
      "incorrect_answers": [
        "Triangle Trade",
        "Transatlantic Slave Trade",
        "The Silk Road"
      ]
    },
    {
      "category": "History",
      "type": "multiple",
      "difficulty": "medium",
      "question": "Which American civilization is the source of the belief that the world would end or drastically change on December 21st, 2012?",
      "correct_answer": "The Mayans",
      "incorrect_answers": [
        "The Incas",
        "The Aztecs",
        "The Navajos"
      ]
    },
    {
      "category": "History",
      "type": "multiple",
      "difficulty": "easy",
      "question": "Who was the first prime minister of Canada?",
      "correct_answer": "John Macdonald",
      "incorrect_answers": [
        "John Abbott",
        "Alexander Mackenzie",
        "Robert Borden"
      ]
    },
    {
      "category": "History",
      "type": "multiple",
      "difficulty": "easy",
      "question": "How was Socrates executed?",
      "correct_answer": "Poison",
      "incorrect_answers": [
        "Decapitation",
        "Firing squad",
        "Crucifixion "
      ]
    },
    {
      "category": "History",
      "type": "multiple",
      "difficulty": "medium",
      "question": "Which historical conflict killed the most people?",
      "correct_answer": "World War II",
      "incorrect_answers": [
        "Taiping Rebellion",
        "Three Kingdoms War",
        "Mongol conquests"
      ]
    },
    {
      "category": "History",
      "type": "multiple",
      "difficulty": "medium",
      "question": "Who is attributed credit for recording the epic poem The Odyssey?",
      "correct_answer": "Homer",
      "incorrect_answers": [
        "Aristotle",
        "Odysseus",
        "Socrates"
      ]
    },
    {
      "category": "History",
      "type": "multiple",
      "difficulty": "easy",
      "question": "In 1939, Britain and France declared war on Germany after it invaded which country?",
      "correct_answer": "Poland",
      "incorrect_answers": [
        "Czechoslovakia",
        "Austria",
        "Hungary"
      ]
    },
    {
      "category": "History",
      "type": "multiple",
      "difficulty": "medium",
      "question": "The United States Army Air Corps became the United States Air Force on what date?",
      "correct_answer": "September 18, 1947",
      "incorrect_answers": [
        "December 14, 1946",
        "October 27, 1945",
        "November 08, 1944"
      ]
    },
    {
      "category": "History",
      "type": "multiple",
      "difficulty": "medium",
      "question": "Which of the following countries was the first to send an object into space?",
      "correct_answer": "Germany",
      "incorrect_answers": [
        "USA",
        "Russia",
        "China"
      ]
    },
    {
      "category": "History",
      "type": "multiple",
      "difficulty": "medium",
      "question": "In what year did the Berlin Wall fall?",
      "correct_answer": "1989",
      "incorrect_answers": [
        "1987",
        "1991",
        "1993"
      ]
    },
    {
      "category": "History",
      "type": "multiple",
      "difficulty": "hard",
      "question": "What was the name of the German offensive operation in October 1941 to take Moscow before winter?",
      "correct_answer": "Operation Typhoon",
      "incorrect_answers": [
        "Operation Sunflower",
        "Operation Barbarossa",
        "Case Blue"
      ]
    },
    {
      "category": "History",
      "type": "multiple",
      "difficulty": "hard",
      "question": "When was the &quot;Siege of Leningrad&quot; lifted during World War II?",
      "correct_answer": "January 1944",
      "incorrect_answers": [
        "September 1943",
        "November 1943",
        "March 1944"
      ]
    },
    {
      "category": "History",
      "type": "multiple",
      "difficulty": "medium",
      "question": "Which country gifted the Statue of Liberty to the United States of America?",
      "correct_answer": "France",
      "incorrect_answers": [
        "Spain",
        "England",
        "Germany"
      ]
    },
    {
      "category": "History",
      "type": "multiple",
      "difficulty": "easy",
      "question": "Who led the Communist Revolution of Russia?",
      "correct_answer": "Vladimir Lenin",
      "incorrect_answers": [
        "Joseph Stalin",
        "Vladimir Putin",
        "Mikhail Gorbachev"
      ]
    },
    {
      "category": "History",
      "type": "multiple",
      "difficulty": "easy",
      "question": "What is the historical name of Sri Lanka?",
      "correct_answer": "Ceylon",
      "incorrect_answers": [
        "Myanmar",
        "Colombo",
        "Badulla"
      ]
    },
    {
      "category": "History",
      "type": "multiple",
      "difficulty": "easy",
      "question": "In 1453, which important city fell?",
      "correct_answer": "Constantinople",
      "incorrect_answers": [
        "Rome",
        "Hamburg",
        "Athens"
      ]
    },
    {
      "category": "History",
      "type": "multiple",
      "difficulty": "medium",
      "question": "The Korean War started in what year?",
      "correct_answer": "1950",
      "incorrect_answers": [
        "1945",
        "1960",
        "1912"
      ]
    },
    {
      "category": "History",
      "type": "multiple",
      "difficulty": "hard",
      "question": "The ancient city of Chich&eacute;n Itz&aacute; was built by which civilization?",
      "correct_answer": "Mayans",
      "incorrect_answers": [
        "Aztecs",
        "Incas",
        "Toltecs"
      ]
    },
    {
      "category": "History",
      "type": "multiple",
      "difficulty": "medium",
      "question": "What was the name of the planned invasion of Japan towards the end of World War II?",
      "correct_answer": "Operation Downfall",
      "incorrect_answers": [
        "Operation Boarding Party",
        "Operation Ironclad",
        "Operation Aflame"
      ]
    },
    {
      "category": "History",
      "type": "multiple",
      "difficulty": "hard",
      "question": "Who was the first man to travel into outer space twice?",
      "correct_answer": "Gus Grissom",
      "incorrect_answers": [
        "Vladimir Komarov",
        "Charles Conrad",
        "Yuri Gagarin"
      ]
    },
    {
      "category": "History",
      "type": "multiple",
      "difficulty": "hard",
      "question": "During World War I, which nation&#039;s monarchs were blood related?",
      "correct_answer": "England, Germany, Russia",
      "incorrect_answers": [
        "France, Russia, Germany",
        "Serbia, Russia, Croatia",
        "Germany, Spain, Austria"
      ]
    },
    {
      "category": "History",
      "type": "multiple",
      "difficulty": "easy",
      "question": "What does the United States of America celebrate during the 4th of July?",
      "correct_answer": "The signing of the Declaration of Independence",
      "incorrect_answers": [
        "The anniversary of the Battle of Gettysburg",
        "The crossing of the Delaware River",
        "The ratification of the Constitution"
      ]
    },
    {
      "category": "History",
      "type": "multiple",
      "difficulty": "medium",
      "question": "During which American Civil War campaign did Union troops dig a tunnel beneath Confederate troops to detonate explosives underneath them?",
      "correct_answer": "Siege of Petersburg",
      "incorrect_answers": [
        "Siege of Vicksburg",
        "Antietam Campaign",
        "Gettysburg Campagin"
      ]
    },
    {
      "category": "History",
      "type": "multiple",
      "difficulty": "hard",
      "question": "The Bohemian Revolt (1618-1620) started after Protestants in Prague did what to their Catholic Lords Regents?",
      "correct_answer": "Threw them out of a window",
      "incorrect_answers": [
        "Insulted their mothers",
        "Locked them in stockades",
        "Hung them."
      ]
    },
    {
      "category": "History",
      "type": "multiple",
      "difficulty": "medium",
      "question": "The Thirty Years War ended with which treaty?",
      "correct_answer": "Peace of Westphalia",
      "incorrect_answers": [
        "Treaty of Versailles",
        "Treaty of Paris",
        "Peace of Prague"
      ]
    },
    {
      "category": "History",
      "type": "multiple",
      "difficulty": "hard",
      "question": "Who is the creator of the soft drink, Dr. Pepper?",
      "correct_answer": "Charles Alderton",
      "incorrect_answers": [
        "James Wellington",
        "Johnson Hinsin",
        "Boris Heviltik"
      ]
    },
    {
      "category": "History",
      "type": "multiple",
      "difficulty": "hard",
      "question": "What is the name of the Boeing B-29 that dropped the &#039;Little Boy&#039; atomic bomb on Hiroshima?",
      "correct_answer": "Enola Gay",
      "incorrect_answers": [
        "Necessary Evil",
        "The Great Artiste",
        "Full House"
      ]
    },
    {
      "category": "History",
      "type": "multiple",
      "difficulty": "easy",
      "question": "What country joined the EU in 2013?",
      "correct_answer": "Croatia",
      "incorrect_answers": [
        "Bulgaria",
        "Slovenia",
        "Turkey"
      ]
    },
    {
      "category": "Animals",
      "type": "multiple",
      "difficulty": "hard",
      "question": "What was the name of the Ethiopian Wolf before they knew it was related to wolves?",
      "correct_answer": "Simien Jackel",
      "incorrect_answers": [
        "Ethiopian Coyote",
        "Amharic Fox",
        "Canis Simiensis"
      ]
    },
    {
      "category": "Animals",
      "type": "multiple",
      "difficulty": "medium",
      "question": "What does &quot;hippopotamus&quot; mean and in what langauge?",
      "correct_answer": "River Horse (Greek)",
      "incorrect_answers": [
        "River Horse (Latin)",
        "Fat Pig (Greek)",
        "Fat Pig (Latin)"
      ]
    },
    {
      "category": "Animals",
      "type": "multiple",
      "difficulty": "medium",
      "question": "A carnivorous animal eats flesh, what does a nucivorous animal eat?",
      "correct_answer": "Nuts",
      "incorrect_answers": [
        "Nothing",
        "Fruit",
        "Seaweed"
      ]
    },
    {
      "category": "Animals",
      "type": "multiple",
      "difficulty": "medium",
      "question": "What type of animal is a natterjack?",
      "correct_answer": "Toad",
      "incorrect_answers": [
        "Bird",
        "Fish",
        "Insect"
      ]
    },
    {
      "category": "Animals",
      "type": "multiple",
      "difficulty": "easy",
      "question": "What is the fastest  land animal?",
      "correct_answer": "Cheetah",
      "incorrect_answers": [
        "Lion",
        "Thomson&rsquo;s Gazelle",
        "Pronghorn Antelope"
      ]
    },
    {
      "category": "Animals",
      "type": "multiple",
      "difficulty": "easy",
      "question": "What is the scientific name for modern day humans?",
      "correct_answer": "Homo Sapiens",
      "incorrect_answers": [
        "Homo Ergaster",
        "Homo Erectus",
        "Homo Neanderthalensis"
      ]
    },
    {
      "category": "Animals",
      "type": "multiple",
      "difficulty": "easy",
      "question": "The Kākāpō is a large, flightless, nocturnal parrot native to which country?",
      "correct_answer": "New Zealand",
      "incorrect_answers": [
        "South Africa",
        "Australia",
        "Madagascar"
      ]
    },
    {
      "category": "Animals",
      "type": "multiple",
      "difficulty": "hard",
      "question": "Which species of Brown Bear is not extinct?",
      "correct_answer": "Syrian Brown Bear",
      "incorrect_answers": [
        "California Grizzly Bear",
        "Atlas Bear",
        "Mexican Grizzly Bear"
      ]
    },
    {
      "category": "Animals",
      "type": "multiple",
      "difficulty": "medium",
      "question": "What color/colour is a polar bear&#039;s skin?",
      "correct_answer": "Black",
      "incorrect_answers": [
        "White",
        "Pink",
        "Green"
      ]
    },
    {
      "category": "Animals",
      "type": "multiple",
      "difficulty": "easy",
      "question": "Hippocampus is the Latin name for which marine creature?",
      "correct_answer": "Seahorse",
      "incorrect_answers": [
        "Dolphin",
        "Whale",
        "Octopus"
      ]
    },
    {
      "category": "Animals",
      "type": "multiple",
      "difficulty": "medium",
      "question": "Cashmere is the wool from which kind of animal?",
      "correct_answer": "Goat",
      "incorrect_answers": [
        "Sheep",
        "Camel",
        "Llama"
      ]
    },
    {
      "category": "Animals",
      "type": "multiple",
      "difficulty": "medium",
      "question": "What is the scientific name for the &quot;Polar Bear&quot;?",
      "correct_answer": "Ursus Maritimus",
      "incorrect_answers": [
        "Polar Bear",
        "Ursus Spelaeus",
        "Ursus Arctos"
      ]
    },
    {
      "category": "Animals",
      "type": "multiple",
      "difficulty": "medium",
      "question": "What are rhino&#039;s horn made of?",
      "correct_answer": "Keratin",
      "incorrect_answers": [
        "Bone",
        "Ivory",
        "Skin"
      ]
    },
    {
      "category": "Animals",
      "type": "multiple",
      "difficulty": "easy",
      "question": "How many legs do butterflies have?",
      "correct_answer": "6",
      "incorrect_answers": [
        "2",
        "4",
        "0"
      ]
    },
    {
      "category": "Animals",
      "type": "multiple",
      "difficulty": "hard",
      "question": "What scientific suborder does the family Hyaenidae belong to?",
      "correct_answer": "Feliformia",
      "incorrect_answers": [
        "Haplorhini",
        "Caniformia",
        "Ciconiiformes"
      ]
    },
    {
      "category": "Animals",
      "type": "multiple",
      "difficulty": "hard",
      "question": "How many known living species of hyenas are there?",
      "correct_answer": "4",
      "incorrect_answers": [
        "8",
        "2",
        "6"
      ]
    },
    {
      "category": "Animals",
      "type": "multiple",
      "difficulty": "hard",
      "question": "What scientific family does the Aardwolf belong to?",
      "correct_answer": "Hyaenidae",
      "incorrect_answers": [
        "Canidae",
        "Felidae",
        "Eupleridae"
      ]
    },
    {
      "category": "Animals",
      "type": "multiple",
      "difficulty": "medium",
      "question": "For what reason would a spotted hyena &quot;laugh&quot;?",
      "correct_answer": "Nervousness",
      "incorrect_answers": [
        "Excitement",
        "Aggression",
        "Exhaustion"
      ]
    },
    {
      "category": "Animals",
      "type": "multiple",
      "difficulty": "easy",
      "question": "What do you call a baby bat?",
      "correct_answer": "Pup",
      "incorrect_answers": [
        "Cub",
        "Chick",
        "Kid"
      ]
    },
    {
      "category": "Animals",
      "type": "multiple",
      "difficulty": "hard",
      "question": "What is the scientific name of the cheetah?",
      "correct_answer": "Acinonyx jubatus",
      "incorrect_answers": [
        "Panthera onca",
        "Lynx rufus",
        "Felis catus"
      ]
    },
    {
      "category": "Animals",
      "type": "multiple",
      "difficulty": "hard",
      "question": "What is the scientific name of the Budgerigar?",
      "correct_answer": "Melopsittacus undulatus",
      "incorrect_answers": [
        "Nymphicus hollandicus",
        "Pyrrhura molinae",
        "Ara macao"
      ]
    },
    {
      "category": "Animals",
      "type": "multiple",
      "difficulty": "medium",
      "question": "Which animal was part of an Russian domestication experiment in 1959?",
      "correct_answer": "Foxes",
      "incorrect_answers": [
        "Pigeons",
        "Bears",
        "Alligators"
      ]
    },
    {
      "category": "Animals",
      "type": "multiple",
      "difficulty": "medium",
      "question": "The now extinct species &quot;Thylacine&quot; was native to where?",
      "correct_answer": "Tasmania, Australia",
      "incorrect_answers": [
        "Baluchistan, Pakistan",
        "Wallachia, Romania",
        "Oregon, United States"
      ]
    },
    {
      "category": "Animals",
      "type": "multiple",
      "difficulty": "hard",
      "question": "What is the Gray Wolf&#039;s scientific name?",
      "correct_answer": "Canis Lupus",
      "incorrect_answers": [
        "Canis Aureus",
        "Canis Latrans",
        "Canis Lupus Lycaon"
      ]
    },
    {
      "category": "Animals",
      "type": "multiple",
      "difficulty": "hard",
      "question": "Which of these animals is NOT a lizard?",
      "correct_answer": "Tuatara",
      "incorrect_answers": [
        "Komodo Dragon",
        "Gila Monster",
        "Green Iguana"
      ]
    },
    {
      "category": "Animals",
      "type": "multiple",
      "difficulty": "easy",
      "question": "What is Grumpy Cat&#039;s real name?",
      "correct_answer": "Tardar Sauce",
      "incorrect_answers": [
        "Sauce",
        "Minnie",
        "Broccoli"
      ]
    },
    {
      "category": "Animals",
      "type": "multiple",
      "difficulty": "hard",
      "question": "What type of creature is a Bonobo?",
      "correct_answer": "Ape",
      "incorrect_answers": [
        "Lion",
        "Parrot",
        "Wildcat"
      ]
    },
    {
      "category": "Animals",
      "type": "multiple",
      "difficulty": "medium",
      "question": "Which of these species is not extinct?",
      "correct_answer": "Komodo dragon",
      "incorrect_answers": [
        "Japanese sea lion",
        "Tasmanian tiger",
        "Saudi gazelle"
      ]
    },
    {
      "category": "Animals",
      "type": "multiple",
      "difficulty": "easy",
      "question": "Which class of animals are newts members of?",
      "correct_answer": "Amphibian",
      "incorrect_answers": [
        "Fish",
        "Reptiles",
        "Mammals"
      ]
    },
    {
      "category": "Animals",
      "type": "multiple",
      "difficulty": "medium",
      "question": "What is the name of the family that the domestic cat is a member of?",
      "correct_answer": "Felidae",
      "incorrect_answers": [
        "Felinae",
        "Felis",
        "Cat"
      ]
    },
    {
      "category": "Animals",
      "type": "multiple",
      "difficulty": "medium",
      "question": "What dog bread is one of the oldest breeds of dog and has flourished since before 400 BCE.",
      "correct_answer": "Pugs",
      "incorrect_answers": [
        "Bulldogs",
        "Boxers",
        "Chihuahua"
      ]
    },
    {
      "category": "Animals",
      "type": "multiple",
      "difficulty": "hard",
      "question": "What is the name of the copper-rich protein that creates the blue blood in the Antarctic octopus?",
      "correct_answer": "Hemocyanin",
      "incorrect_answers": [
        "Cytochrome",
        "Iron",
        "Methionine"
      ]
    },
    {
      "category": "Animals",
      "type": "multiple",
      "difficulty": "hard",
      "question": "Which species is a &quot;mountain chicken&quot;?",
      "correct_answer": "Frog",
      "incorrect_answers": [
        "Chicken",
        "Horse",
        "Fly"
      ]
    },
    {
      "category": "Animals",
      "type": "multiple",
      "difficulty": "medium",
      "question": "What is the fastest animal?",
      "correct_answer": "Peregrine Falcon",
      "incorrect_answers": [
        "Golden Eagle",
        "Cheetah",
        "Horsefly"
      ]
    },
    {
      "category": "Animals",
      "type": "multiple",
      "difficulty": "medium",
      "question": "The dish Fugu, is made from what family of fish?",
      "correct_answer": "Pufferfish",
      "incorrect_answers": [
        "Bass",
        "Salmon",
        "Mackerel"
      ]
    },
    {
      "category": "Animals",
      "type": "multiple",
      "difficulty": "easy",
      "question": "What is the collective noun for a group of crows?",
      "correct_answer": "Murder",
      "incorrect_answers": [
        "Pack",
        "Gaggle",
        "Herd"
      ]
    },
    {
      "category": "Animals",
      "type": "multiple",
      "difficulty": "hard",
      "question": "Which of the following is another name for the &quot;Poecilotheria Metallica Tarantula&quot;?",
      "correct_answer": "Gooty",
      "incorrect_answers": [
        "Hopper",
        "Silver Stripe",
        "Woebegone"
      ]
    },
    {
      "category": "Animals",
      "type": "multiple",
      "difficulty": "medium",
      "question": "What is the scientific name of the Common Chimpanzee?",
      "correct_answer": "Pan troglodytes",
      "incorrect_answers": [
        "Gorilla gorilla",
        "Pan paniscus",
        "Panthera leo"
      ]
    },
    {
      "category": "Animals",
      "type": "multiple",
      "difficulty": "easy",
      "question": "By definition, where does an abyssopelagic animal live?",
      "correct_answer": "At the bottom of the ocean",
      "incorrect_answers": [
        "In the desert",
        "On top of a mountain",
        "Inside a tree"
      ]
    },
    {
      "category": "Animals",
      "type": "multiple",
      "difficulty": "hard",
      "question": "Which of these is a colony of polyps and not a jellyfish?",
      "correct_answer": "Portuguese Man-of-War",
      "incorrect_answers": [
        "Sea Wasp",
        "Irukandji",
        "Sea Nettle"
      ]
    },
    {
      "category": "Animals",
      "type": "multiple",
      "difficulty": "easy",
      "question": "What colour is the female blackbird?",
      "correct_answer": "Brown",
      "incorrect_answers": [
        "Black",
        "White",
        "Yellow"
      ]
    },
    {
      "category": "Animals",
      "type": "multiple",
      "difficulty": "easy",
      "question": "How many teeth does an adult rabbit have?",
      "correct_answer": "28",
      "incorrect_answers": [
        "30",
        "26",
        "24"
      ]
    },
    {
      "category": "Animals",
      "type": "multiple",
      "difficulty": "medium",
      "question": "What is the name for a male bee that comes from an unfertilized egg?",
      "correct_answer": "Drone",
      "incorrect_answers": [
        "Soldier",
        "Worker",
        "Male"
      ]
    },
    {
      "category": "Animals",
      "type": "multiple",
      "difficulty": "easy",
      "question": "What is the name of a rabbit&#039;s abode?",
      "correct_answer": "Burrow",
      "incorrect_answers": [
        "Nest",
        "Den",
        "Dray"
      ]
    },
    {
      "category": "Animals",
      "type": "multiple",
      "difficulty": "medium",
      "question": "What is the collective noun for bears?",
      "correct_answer": "Sloth",
      "incorrect_answers": [
        "Drove",
        "Tribe",
        "Husk"
      ]
    },
    {
      "category": "Animals",
      "type": "multiple",
      "difficulty": "medium",
      "question": "What is the collective noun for rats?",
      "correct_answer": "Mischief",
      "incorrect_answers": [
        "Pack",
        "Race",
        "Drift"
      ]
    },
    {
      "category": "Animals",
      "type": "multiple",
      "difficulty": "hard",
      "question": "What is the collective noun for vultures?",
      "correct_answer": "Wake",
      "incorrect_answers": [
        "Ambush",
        "Building",
        "Gaze"
      ]
    },
    {
      "category": "Animals",
      "type": "multiple",
      "difficulty": "hard",
      "question": "What bird is born with claws on its wing digits?",
      "correct_answer": "Hoatzin",
      "incorrect_answers": [
        "Cormorant",
        "Cassowary",
        "Secretary bird"
      ]
    },
    {
      "category": "Animals",
      "type": "multiple",
      "difficulty": "medium",
      "question": "&quot;Decapods&quot; are an order of ten-footed crustaceans.  Which of these are NOT decapods?",
      "correct_answer": "Krill",
      "incorrect_answers": [
        "Lobsters",
        "Shrimp",
        "Crabs"
      ]
    },
    {
      "category": "Animals",
      "type": "multiple",
      "difficulty": "medium",
      "question": "What is the world&#039;s longest venomous snake?",
      "correct_answer": "King Cobra",
      "incorrect_answers": [
        "Green Anaconda",
        "Inland Taipan",
        "Yellow Bellied Sea Snake"
      ]
    }
  ]
}